setup.py
JSTInteract/JSTInteract.py
JSTInteract/davlib.py
JSTInteract/qp_xml.py
JSTInteract.egg-info/PKG-INFO
JSTInteract.egg-info/SOURCES.txt
JSTInteract.egg-info/dependency_links.txt
JSTInteract.egg-info/top_level.txt