Metadata-Version: 1.1
Name: JSTInteract
Version: 0.01
Summary: JST Client for running phylogenetic web services from IPython Notebook
Home-page: http://github.com/svicario/PhyloHWS
Author: Saverio Vicario, Giacinto Donvito
Author-email: UNKNOWN
License: UNKNOWN
Platform: UNKNOWN
Classifier: Development Status :: 3 - Alpha
Classifier: Topic :: Utilities
Classifier: License :: OSI Approved :: MIT License
Classifier: Intended Audience :: Science/Research
Classifier: Programming Language :: Python :: 2.7
Classifier: Topic :: Scientific/Engineering
